buildbot_react_wsgi_dashboards/VERSION
buildbot_react_wsgi_dashboards/__init__.py
buildbot_react_wsgi_dashboards/static/scripts.js
buildbot_react_wsgi_dashboards-4.0.4.dist-info/METADATA
buildbot_react_wsgi_dashboards-4.0.4.dist-info/WHEEL
buildbot_react_wsgi_dashboards-4.0.4.dist-info/entry_points.txt
buildbot_react_wsgi_dashboards-4.0.4.dist-info/top_level.txt
buildbot_react_wsgi_dashboards-4.0.4.dist-info/RECORD
