Metadata-Version: 2.1
Name: buildbot-react-wsgi-dashboards
Version: 4.0.4
Summary: Buildbot plugin to integrate flask or bottledashboards to buildbot UI (React)
Home-page: http://buildbot.net/
Author: Buildbot maintainers
Author-email: devel@buildbot.net
Classifier: License :: OSI Approved :: GNU General Public License v2 (GPLv2)
